{
    "annotations": {
        "list": [
            {
                "builtIn": 1,
                "datasource": "-- Grafana --",
                "enable": true,
                "hide": true,
                "iconColor": "rgba(0, 211, 255, 1)",
                "name": "Annotations & Alerts",
                "type": "dashboard"
            }
        ]
    },
    "editable": true,
    "gnetId": null,
    "graphTooltip": 0,
    "id": null,
    "links": [],
    "panels": [
        {
            "datasource": "Prometheus",
            "fieldConfig": {
                "defaults": {
                    "color": {
                        "mode": "palette-classic"
                    },
                    "custom": {
                        "axisLabel": "",
                        "axisPlacement": "auto",
                        "barAlignment": 0,
                        "drawStyle": "line",
                        "fillOpacity": 10,
                        "gradientMode": "none",
                        "hideFrom": {
                            "tooltip": false,
                            "viz": false,
                            "legend": false
                        },
                        "lineInterpolation": "linear",
                        "lineWidth": 1,
                        "pointSize": 5,
                        "scaleDistribution": {
                            "type": "linear"
                        },
                        "showPoints": "never",
                        "spanNulls": true
                    },
                    "mappings": [],
                    "thresholds": {
                        "mode": "absolute",
                        "steps": [
                            {
                                "color": "green",
                                "value": null
                            }
                        ]
                    },
                    "unit": "short"
                },
                "overrides": []
            },
            "gridPos": {
                "h": 8,
                "w": 12,
                "x": 0,
                "y": 0
            },
            "id": 2,
            "options": {
                "legend": {
                    "calcs": [],
                    "displayMode": "list",
                    "placement": "bottom"
                },
                "tooltip": {
                    "mode": "single"
                }
            },
            "pluginVersion": "8.0.0",
            "targets": [
                {
                    "expr": "up",
                    "refId": "A"
                }
            ],
            "title": "Service Health",
            "type": "timeseries"
        },
        {
            "datasource": "Prometheus",
            "fieldConfig": {
                "defaults": {
                    "color": {
                        "mode": "thresholds"
                    },
                    "mappings": [],
                    "thresholds": {
                        "mode": "absolute",
                        "steps": [
                            {
                                "color": "green",
                                "value": null
                            }
                        ]
                    }
                },
                "overrides": []
            },
            "gridPos": {
                "h": 8,
                "w": 12,
                "x": 12,
                "y": 0
            },
            "id": 4,
            "options": {
                "orientation": "auto",
                "reduceOptions": {
                    "values": false,
                    "calcs": [
                        "lastNotNull"
                    ],
                    "fields": ""
                },
                "showThresholdLabels": false,
                "showThresholdMarkers": true,
                "text": {}
            },
            "pluginVersion": "8.0.0",
            "targets": [
                {
                    "expr": "sum(up)",
                    "refId": "A"
                }
            ],
            "title": "Services Up",
            "type": "gauge"
        },
        {
            "datasource": "Loki",
            "gridPos": {
                "h": 8,
                "w": 24,
                "x": 0,
                "y": 8
            },
            "id": 6,
            "options": {
                "showLabels": false,
                "showTime": true,
                "sortOrder": "Descending",
                "wrapLogMessage": true
            },
            "targets": [
                {
                    "expr": "{job=~\".+\"}",
                    "refId": "A"
                }
            ],
            "title": "Application Logs",
            "type": "logs"
        },
        {
            "datasource": "Tempo",
            "gridPos": {
                "h": 8,
                "w": 24,
                "x": 0,
                "y": 16
            },
            "id": 8,
            "targets": [
                {
                    "query": "",
                    "refId": "A"
                }
            ],
            "title": "Traces",
            "type": "traces"
        }
    ],
    "schemaVersion": 27,
    "style": "dark",
    "tags": [
        "multi-tenant",
        "observability"
    ],
    "templating": {
        "list": []
    },
    "time": {
        "from": "now-6h",
        "to": "now"
    },
    "timepicker": {},
    "timezone": "",
    "title": "Multi-Tenant App Overview",
    "uid": "multitenantapp",
    "version": 0
}